app/__init__.py
app/config.py
app/db.py
app/main.py
app/clients/__init__.py
app/clients/synthwell_client.py
app/gateway/__init__.py
app/gateway/auth.py
app/gateway/router.py
app/gateway/session.py
app/mcp/__init__.py
app/mcp/server.py
app/mcp/tools/__init__.py
app/mcp/tools/cohort.py
app/mcp/tools/execution.py
app/mcp/tools/journey.py
app/mcp/tools/simulation.py
app/models/__init__.py
app/models/schemas.py
terryann_core-0.1.0.dist-info/METADATA
terryann_core-0.1.0.dist-info/WHEEL
terryann_core-0.1.0.dist-info/RECORD
